advertion/__init__.py
advertion/core.py
advertion/public.py
advertion/version.py
advertion-1.0.1.dist-info/METADATA
advertion-1.0.1.dist-info/WHEEL
advertion-1.0.1.dist-info/RECORD
