Metadata-Version: 2.1
Name: advertion
Version: 1.0.1
Summary: A tiny framework to perform adversarial validation of your training and test data.
Home-page: https://pypi.org/project/advertion
License: Apache-2.0
Keywords: adversarial-validation,data-drift,machine-learning
Author: Ilias Antonopoulos
Author-email: ilias.antonopoulos@yahoo.gr
Requires-Python: >=3.9,<3.12
Classifier: Development Status :: 5 - Production/Stable
Classifier: Intended Audience :: Developers
Classifier: Intended Audience :: Education
Classifier: Intended Audience :: Information Technology
Classifier: Intended Audience :: Science/Research
Classifier: License :: OSI Approved :: Apache Software License
Classifier: Natural Language :: English
Classifier: Operating System :: OS Independent
Classifier: Programming Language :: Python :: 3
Classifier: Programming Language :: Python :: 3.9
Classifier: Programming Language :: Python :: 3.10
Classifier: Programming Language :: Python :: 3.11
Classifier: Programming Language :: Python :: 3 :: Only
Classifier: Topic :: Software Development :: Libraries :: Python Modules
Requires-Dist: pandas (>=2.0.3,<2.1.0)
Requires-Dist: pydantic (>=2.0.3,<2.1.0)
Requires-Dist: scikit-learn (>=1.3.0,<1.4.0)
Requires-Dist: scipy (>=1.10.1,<1.11.0)
Requires-Dist: xgboost (>=1.7.6,<1.8.0)
Project-URL: Bug Tracker, https://github.com/ilias-ant/adversarial-validation/issues
Project-URL: Repository, https://github.com/ilias-ant/adversarial-validation
